README.md
setup.cfg
setup.py
nbody/__init__.py
nbody.egg-info/PKG-INFO
nbody.egg-info/SOURCES.txt
nbody.egg-info/dependency_links.txt
nbody.egg-info/requires.txt
nbody.egg-info/top_level.txt
nbody/config/default_params.py
nbody/core/Sphere.py
nbody/core/System.py
nbody/core/__init__.py
nbody/lib/__init__.py
nbody/lib/generators.py
nbody/lib/io.py
nbody/lib/visualizer.py
nbody/utils/Counter.py
nbody/utils/__init__.py
nbody/utils/checking.py
nbody/utils/exceptions.py
nbody/utils/validation.py
sample/collision_lattice_2D.py
sample/collision_lattice_3D.py
sample/orbits.py
sample/railgun.py
sample/random_particles_2D.py
sample/random_particles_3D.py