Metadata-Version: 1.2
Name: nbody
Version: 0.0.4
Summary: GPU-accelerated N-Body particle simulator with visualizer
Home-page: https://github.com/GabrielSCabrera/nBody
Author: Gabriel S. Cabrera
Author-email: gabric@uio.no
License: GPLv3
Platform: UNKNOWN
Classifier: Development Status :: 2 - Pre-Alpha
Classifier: License :: OSI Approved :: GNU General Public License v3 (GPLv3)
Classifier: Programming Language :: Python :: 3.6
Classifier: Topic :: Software Development :: Libraries
Classifier: Topic :: Software Development :: Libraries :: Python Modules
Classifier: Topic :: Scientific/Engineering :: Physics
Classifier: Topic :: Scientific/Engineering :: Visualization
Classifier: Intended Audience :: Science/Research
Classifier: Intended Audience :: Education
Requires-Python: >=3.6.8
